AmaFree/__init__.py
AmaFree/asb.py
advanced_scorecard_builder-1.0.2.dist-info/METADATA
advanced_scorecard_builder-1.0.2.dist-info/RECORD
advanced_scorecard_builder-1.0.2.dist-info/WHEEL
advanced_scorecard_builder-1.0.2.dist-info/top_level.txt
