Metadata-Version: 2.1
Name: advanced-scorecard-builder
Version: 1.0.2
Summary: AMA Institute - Advanced Scorecard Builder Free version
Home-page: http://amainstitute.pl
Author: s.zajac
Author-email: s.zajac@amainstitute.pl
License: UNKNOWN
Project-URL: Source, https://amainstitute.pl/ama-advanced-scorecard-builder/#start
Project-URL: Documentation, https://amainstitute.pl/ama-advanced-scorecard-builder/
Keywords: AMA Institute,AMA,ASB,Scorecard,AMA Scorecard
Platform: Linux
Platform: Windows
Platform: Mac OS X
Classifier: Operating System :: OS Independent
Classifier: Intended Audience :: Developers
Classifier: License :: OSI Approved :: MIT License
Classifier: Programming Language :: Python :: 3
Classifier: Programming Language :: Python :: 3.5
Classifier: Topic :: Utilities
Requires-Dist: numpy (>=1.11.3)
Requires-Dist: pandas (>=0.19.2)
Requires-Dist: matplotlib (>=2.0.0)
Requires-Dist: regressors
